Metadata-Version: 1.0
Name: matrix-revolution
Version: 1.1
Summary: Matrix operations
Home-page: UNKNOWN
Author: Rupali Sinha
Author-email: UNKNOWN
License: UNKNOWN
Platform: UNKNOWN
